quickstatements_client/__init__.py
quickstatements_client/__main__.py
quickstatements_client/cli.py
quickstatements_client/client.py
quickstatements_client/constants.py
quickstatements_client/model.py
quickstatements_client/py.typed
quickstatements_client/version.py
quickstatements_client/language_codes/__init__.py
quickstatements_client/language_codes/data.json
quickstatements_client/maintenance/__init__.py
quickstatements_client/maintenance/annotate_missing_followed_by.py
quickstatements_client/maintenance/annotate_missing_follows.py
quickstatements_client/sources/__init__.py
quickstatements_client/sources/licenses.json
quickstatements_client/sources/orcid.py
quickstatements_client/sources/pypi.py
quickstatements_client/sources/utils.py
quickstatements_client-0.1.1.dist-info/LICENSE
quickstatements_client-0.1.1.dist-info/METADATA
quickstatements_client-0.1.1.dist-info/WHEEL
quickstatements_client-0.1.1.dist-info/entry_points.txt
quickstatements_client-0.1.1.dist-info/top_level.txt
quickstatements_client-0.1.1.dist-info/RECORD
