Metadata-Version: 2.1
Name: quickstatements_client
Version: 0.1.1
Summary: A data model and client for Wikidata QuickStatements
Home-page: https://github.com/cthoyt/quickstatements_client
Download-URL: https://github.com/cthoyt/quickstatements_client/releases
Author: Charles Tapley Hoyt
Author-email: cthoyt@gmail.com
Maintainer: Charles Tapley Hoyt
Maintainer-email: cthoyt@gmail.com
License: MIT
Project-URL: Bug Tracker, https://github.com/cthoyt/quickstatements_client/issues
Project-URL: Source Code, https://github.com/cthoyt/quickstatements_client
Keywords: snekpack,cookiecutter,wikidata,quickstatements,pydantic
Classifier: Development Status :: 1 - Planning
Classifier: Environment :: Console
Classifier: Intended Audience :: Developers
Classifier: License :: OSI Approved :: MIT License
Classifier: Operating System :: OS Independent
Classifier: Framework :: Pytest
Classifier: Framework :: tox
Classifier: Framework :: Sphinx
Classifier: Programming Language :: Python
Classifier: Programming Language :: Python :: 3.9
Classifier: Programming Language :: Python :: 3.10
Classifier: Programming Language :: Python :: 3.11
Classifier: Programming Language :: Python :: 3.12
Classifier: Programming Language :: Python :: 3 :: Only
Requires-Python: >=3.9
License-File: LICENSE
Requires-Dist: click
Requires-Dist: pydantic>=2.0
Requires-Dist: pystow
Requires-Dist: typing-extensions
Provides-Extra: docs
Requires-Dist: sphinx<8.0; extra == "docs"
Requires-Dist: sphinx-rtd-theme; extra == "docs"
Requires-Dist: sphinx-click; extra == "docs"
Requires-Dist: sphinx-automodapi; extra == "docs"
Provides-Extra: tests
Requires-Dist: pytest; extra == "tests"
Requires-Dist: coverage; extra == "tests"
